littlesis/__init__.py
littlesis/littlesis.py
littlesis-0.1.1.dist-info/LICENSE
littlesis-0.1.1.dist-info/WHEEL
littlesis-0.1.1.dist-info/METADATA
littlesis-0.1.1.dist-info/RECORD
