Metadata-Version: 2.1
Name: littlesis
Version: 0.1.1
Summary: Python wrapper for the LittleSis API.
Home-page: https://github.com/brendanmapes/littlesis
License: MIT
Author: Brendan Mapes
Requires-Python: >=3.9,<4.0
Classifier: License :: OSI Approved :: MIT License
Classifier: Programming Language :: Python :: 3
Classifier: Programming Language :: Python :: 3.9
Requires-Dist: pandas (>=1.3.5,<2.0.0)
Requires-Dist: ratelimit (>=2.2.1,<3.0.0)
Requires-Dist: requests (>=2.26.0,<3.0.0)
Project-URL: Documentation, https://littlesis.readthedocs.io/en/main/
Project-URL: Repository, https://github.com/brendanmapes/littlesis
